ecl_api/__about__.py
ecl_api/__init__.py
ecl_api/ecl.py
ecl_api/ecl_entry.py
ecl_api-0.0.3.dist-info/METADATA
ecl_api-0.0.3.dist-info/WHEEL
ecl_api-0.0.3.dist-info/licenses/LICENSE.txt
ecl_api-0.0.3.dist-info/RECORD
