Metadata-Version: 2.4
Name: ecl-api
Version: 0.0.3
Project-URL: Documentation, https://github.com/marcodeltutto/ecl-api#readme
Project-URL: Issues, https://github.com/marcodeltutto/ecl-api/issues
Project-URL: Source, https://github.com/marcodeltutto/ecl-api
Author-email: Marco Del Tutto <marco.deltutto@gmail.com>
License-File: LICENSE.txt
Classifier: Development Status :: 4 - Beta
Classifier: License :: OSI Approved :: MIT License
Classifier: Programming Language :: Python
Classifier: Programming Language :: Python :: 3.8
Classifier: Programming Language :: Python :: 3.9
Classifier: Programming Language :: Python :: 3.10
Classifier: Programming Language :: Python :: 3.11
Classifier: Programming Language :: Python :: 3.12
Classifier: Programming Language :: Python :: Implementation :: CPython
Classifier: Programming Language :: Python :: Implementation :: PyPy
Requires-Python: >=3.8
Requires-Dist: requests
